{
  "image": "H_101_20251024_hiv00015_f008391.jpg",
  "reviewed": true,
  "updated_at": "20260701_151954",
  "boxes": [
    {
      "class_id": 0,
      "class_name": "car",
      "x1": 58.0,
      "y1": 795.0,
      "x2": 393.0,
      "y2": 1045.0,
      "confidence": 0.8926662802696228,
      "origin_line": "L6",
      "destination_line": "L5",
      "turn_name": "M3",
      "source": "metadata"
    },
    {
      "class_id": 0,
      "class_name": "car",
      "x1": 1074.0,
      "y1": 555.0,
      "x2": 1407.0,
      "y2": 730.0,
      "confidence": 0.8926662802696228,
      "origin_line": "",
      "destination_line": "",
      "turn_name": "",
      "source": "metadata"
    },
    {
      "class_id": 0,
      "class_name": "car",
      "x1": 1563.0,
      "y1": 496.0,
      "x2": 1740.0,
      "y2": 602.0,
      "confidence": 0.8926662802696228,
      "origin_line": "",
      "destination_line": "",
      "turn_name": "",
      "source": "metadata"
    },
    {
      "class_id": 0,
      "class_name": "car",
      "x1": 1887.0,
      "y1": 411.0,
      "x2": 1955.0,
      "y2": 470.0,
      "confidence": 0.8926662802696228,
      "origin_line": "",
      "destination_line": "",
      "turn_name": "",
      "source": "metadata"
    },
    {
      "class_id": 0,
      "class_name": "car",
      "x1": 1640.0,
      "y1": 848.0,
      "x2": 1955.0,
      "y2": 1159.0,
      "confidence": 0.8926662802696228,
      "origin_line": "",
      "destination_line": "",
      "turn_name": "",
      "source": "metadata"
    },
    {
      "class_id": 7,
      "class_name": "van-minivan",
      "x1": 2000.0,
      "y1": 408.0,
      "x2": 2081.0,
      "y2": 462.0,
      "confidence": 0.8926662802696228,
      "origin_line": "",
      "destination_line": "",
      "turn_name": "",
      "source": "metadata"
    }
  ]
}