{
  "image": "H_101_20251024_hiv00016_f001824.jpg",
  "reviewed": true,
  "updated_at": "20260623_175904",
  "boxes": [
    {
      "class_id": 0,
      "class_name": "car",
      "x1": 95.4,
      "y1": 711.0,
      "x2": 154.3,
      "y2": 750.6,
      "confidence": 0.377,
      "origin_line": "",
      "destination_line": "",
      "turn_name": "",
      "source": "ai"
    },
    {
      "class_id": 0,
      "class_name": "car",
      "x1": 249.3,
      "y1": 651.1,
      "x2": 295.2,
      "y2": 692.5,
      "confidence": 0.438,
      "origin_line": "",
      "destination_line": "",
      "turn_name": "",
      "source": "ai"
    },
    {
      "class_id": 0,
      "class_name": "car",
      "x1": 304.0,
      "y1": 639.9,
      "x2": 359.8,
      "y2": 686.7,
      "confidence": 0.48,
      "origin_line": "",
      "destination_line": "",
      "turn_name": "",
      "source": "ai"
    },
    {
      "class_id": 13,
      "class_name": "camioneta",
      "x1": 1276.2,
      "y1": 694.8,
      "x2": 1661.4,
      "y2": 982.8,
      "confidence": 0.881,
      "origin_line": "",
      "destination_line": "",
      "turn_name": "",
      "source": "human"
    },
    {
      "class_id": 1,
      "class_name": "mototaxi",
      "x1": 1746.0,
      "y1": 562.5,
      "x2": 1850.4,
      "y2": 711.9,
      "confidence": 0.861,
      "origin_line": "",
      "destination_line": "",
      "turn_name": "",
      "source": "human"
    },
    {
      "class_id": 1,
      "class_name": "mototaxi",
      "x1": 1822.5,
      "y1": 486.0,
      "x2": 1893.6,
      "y2": 583.2,
      "confidence": 0.426,
      "origin_line": "",
      "destination_line": "",
      "turn_name": "",
      "source": "human"
    },
    {
      "class_id": 7,
      "class_name": "van-minivan",
      "x1": 1881.0,
      "y1": 441.9,
      "x2": 1945.8,
      "y2": 517.5,
      "confidence": 0.451,
      "origin_line": "",
      "destination_line": "",
      "turn_name": "",
      "source": "human"
    },
    {
      "class_id": 1,
      "class_name": "mototaxi",
      "x1": 1940.4,
      "y1": 435.6,
      "x2": 1983.6,
      "y2": 499.5,
      "confidence": 0.274,
      "origin_line": "",
      "destination_line": "",
      "turn_name": "",
      "source": "human"
    },
    {
      "class_id": 0,
      "class_name": "car",
      "x1": 1972.761202811929,
      "y1": 426.2696804063051,
      "x2": 2032.963736025518,
      "y2": 477.44183363785567,
      "confidence": null,
      "origin_line": "",
      "destination_line": "",
      "turn_name": "",
      "source": "human"
    },
    {
      "class_id": 1,
      "class_name": "mototaxi",
      "x1": 2059.0515004180734,
      "y1": 421.25280263850607,
      "x2": 2100.189898114026,
      "y2": 471.4215803164969,
      "confidence": null,
      "origin_line": "",
      "destination_line": "",
      "turn_name": "",
      "source": "human"
    }
  ]
}