{
  "image": "H_101_20251024_hiv00014_f026739.jpg",
  "reviewed": true,
  "updated_at": "20260701_144448",
  "boxes": [
    {
      "class_id": 1,
      "class_name": "mototaxi",
      "x1": 491.77888575764143,
      "y1": 665.0,
      "x2": 720.9189867145644,
      "y2": 862.7380462048249,
      "confidence": 0.3611627519130707,
      "origin_line": "L3",
      "destination_line": "L4",
      "turn_name": "M2",
      "source": "human"
    },
    {
      "class_id": 0,
      "class_name": "car",
      "x1": 1369.73249512248,
      "y1": 590.6683968385041,
      "x2": 1601.5122479947975,
      "y2": 772.6006842043175,
      "confidence": null,
      "origin_line": "",
      "destination_line": "",
      "turn_name": "",
      "source": "human"
    },
    {
      "class_id": 1,
      "class_name": "mototaxi",
      "x1": 1544.912587000118,
      "y1": 430.1399079863159,
      "x2": 1625.9412528016987,
      "y2": 509.6397310369234,
      "confidence": null,
      "origin_line": "",
      "destination_line": "",
      "turn_name": "",
      "source": "human"
    },
    {
      "class_id": 13,
      "class_name": "camioneta",
      "x1": 1818.2413675637174,
      "y1": 414.2291737635873,
      "x2": 1906.5384162769813,
      "y2": 498.5127202626118,
      "confidence": null,
      "origin_line": "",
      "destination_line": "",
      "turn_name": "",
      "source": "human"
    },
    {
      "class_id": 1,
      "class_name": "mototaxi",
      "x1": 2047.9018520703078,
      "y1": 408.7361094726908,
      "x2": 2076.949864338799,
      "y2": 454.60139200188746,
      "confidence": null,
      "origin_line": "",
      "destination_line": "",
      "turn_name": "",
      "source": "human"
    }
  ]
}