{
  "image": "H_101_20251024_hiv00018_f001596.jpg",
  "source": "ai",
  "updated_at": "20260624_143109",
  "boxes": [
    {
      "class_id": 0,
      "class_name": "car",
      "x1": 0.3,
      "y1": 802.3,
      "x2": 222.4,
      "y2": 1080.0,
      "confidence": 0.909,
      "origin_line": "",
      "destination_line": "",
      "turn_name": "",
      "source": "ai"
    },
    {
      "class_id": 0,
      "class_name": "car",
      "x1": 249.5,
      "y1": 650.7,
      "x2": 294.1,
      "y2": 688.5,
      "confidence": 0.264,
      "origin_line": "",
      "destination_line": "",
      "turn_name": "",
      "source": "ai"
    },
    {
      "class_id": 5,
      "class_name": "truck",
      "x1": 711.9,
      "y1": 802.8,
      "x2": 1054.8,
      "y2": 1103.4,
      "confidence": 0.492,
      "origin_line": "",
      "destination_line": "",
      "turn_name": "",
      "source": "ai"
    },
    {
      "class_id": 5,
      "class_name": "truck",
      "x1": 1519.2,
      "y1": 481.5,
      "x2": 1648.8,
      "y2": 583.2,
      "confidence": 0.22,
      "origin_line": "",
      "destination_line": "",
      "turn_name": "",
      "source": "ai"
    },
    {
      "class_id": 4,
      "class_name": "person",
      "x1": 1542.6,
      "y1": 478.8,
      "x2": 1566.0,
      "y2": 559.8,
      "confidence": 0.294,
      "origin_line": "",
      "destination_line": "",
      "turn_name": "",
      "source": "ai"
    },
    {
      "class_id": 3,
      "class_name": "motorcycle",
      "x1": 1621.8,
      "y1": 441.7,
      "x2": 1654.2,
      "y2": 494.1,
      "confidence": 0.219,
      "origin_line": "",
      "destination_line": "",
      "turn_name": "",
      "source": "ai"
    },
    {
      "class_id": 3,
      "class_name": "motorcycle",
      "x1": 2152.8,
      "y1": 716.4,
      "x2": 2278.8,
      "y2": 828.9,
      "confidence": 0.762,
      "origin_line": "",
      "destination_line": "",
      "turn_name": "",
      "source": "ai"
    }
  ]
}