{
  "image": "H_101_20251024_hiv00015_f013194.jpg",
  "source": "ai",
  "updated_at": "20260623_162723",
  "boxes": [
    {
      "class_id": 0,
      "class_name": "car",
      "x1": 251.8,
      "y1": 652.5,
      "x2": 294.5,
      "y2": 695.7,
      "confidence": 0.39,
      "origin_line": "",
      "destination_line": "",
      "turn_name": "",
      "source": "ai"
    },
    {
      "class_id": 0,
      "class_name": "car",
      "x1": 315.0,
      "y1": 640.8,
      "x2": 358.2,
      "y2": 668.7,
      "confidence": 0.361,
      "origin_line": "",
      "destination_line": "",
      "turn_name": "",
      "source": "ai"
    },
    {
      "class_id": 0,
      "class_name": "car",
      "x1": 1065.6,
      "y1": 568.3,
      "x2": 1332.0,
      "y2": 727.6,
      "confidence": 0.941,
      "origin_line": "",
      "destination_line": "",
      "turn_name": "",
      "source": "ai"
    },
    {
      "class_id": 0,
      "class_name": "car",
      "x1": 1620.0,
      "y1": 880.2,
      "x2": 1962.0,
      "y2": 1206.0,
      "confidence": 0.95,
      "origin_line": "",
      "destination_line": "",
      "turn_name": "",
      "source": "ai"
    },
    {
      "class_id": 13,
      "class_name": "camioneta",
      "x1": 1785.6,
      "y1": 468.4,
      "x2": 1897.2,
      "y2": 581.8,
      "confidence": 0.639,
      "origin_line": "",
      "destination_line": "",
      "turn_name": "",
      "source": "ai"
    },
    {
      "class_id": 4,
      "class_name": "person",
      "x1": 1785.6,
      "y1": 468.9,
      "x2": 1816.2,
      "y2": 517.5,
      "confidence": 0.241,
      "origin_line": "",
      "destination_line": "",
      "turn_name": "",
      "source": "ai"
    },
    {
      "class_id": 4,
      "class_name": "person",
      "x1": 1809.0,
      "y1": 466.2,
      "x2": 1839.6,
      "y2": 516.6,
      "confidence": 0.266,
      "origin_line": "",
      "destination_line": "",
      "turn_name": "",
      "source": "ai"
    },
    {
      "class_id": 4,
      "class_name": "person",
      "x1": 1812.6,
      "y1": 456.8,
      "x2": 1827.0,
      "y2": 478.3,
      "confidence": 0.307,
      "origin_line": "",
      "destination_line": "",
      "turn_name": "",
      "source": "ai"
    },
    {
      "class_id": 4,
      "class_name": "person",
      "x1": 1835.1,
      "y1": 460.8,
      "x2": 1857.6,
      "y2": 516.6,
      "confidence": 0.368,
      "origin_line": "",
      "destination_line": "",
      "turn_name": "",
      "source": "ai"
    },
    {
      "class_id": 4,
      "class_name": "person",
      "x1": 1854.0,
      "y1": 454.5,
      "x2": 1882.8,
      "y2": 504.9,
      "confidence": 0.611,
      "origin_line": "",
      "destination_line": "",
      "turn_name": "",
      "source": "ai"
    },
    {
      "class_id": 4,
      "class_name": "person",
      "x1": 1882.8,
      "y1": 405.9,
      "x2": 1897.2,
      "y2": 443.7,
      "confidence": 0.296,
      "origin_line": "",
      "destination_line": "",
      "turn_name": "",
      "source": "ai"
    },
    {
      "class_id": 3,
      "class_name": "motorcycle",
      "x1": 1926.0,
      "y1": 988.2,
      "x2": 2041.2,
      "y2": 1067.4,
      "confidence": 0.324,
      "origin_line": "",
      "destination_line": "",
      "turn_name": "",
      "source": "ai"
    },
    {
      "class_id": 4,
      "class_name": "person",
      "x1": 1944.0,
      "y1": 930.6,
      "x2": 2023.2,
      "y2": 1065.6,
      "confidence": 0.492,
      "origin_line": "",
      "destination_line": "",
      "turn_name": "",
      "source": "ai"
    },
    {
      "class_id": 2,
      "class_name": "microbus",
      "x1": 1947.6,
      "y1": 386.5,
      "x2": 2055.6,
      "y2": 461.2,
      "confidence": 0.672,
      "origin_line": "",
      "destination_line": "",
      "turn_name": "",
      "source": "ai"
    }
  ]
}